PyValico-0.0.2.dist-info/LICENSE
PyValico-0.0.2.dist-info/METADATA
PyValico-0.0.2.dist-info/RECORD
PyValico-0.0.2.dist-info/WHEEL
PyValico-0.0.2.dist-info/top_level.txt
valico/__init__.py
valico/valico.cpython-35m-x86_64-linux-gnu.so
